audio/__init__.py
audio/player.py
kukufuckingkan-0.6.dist-info/METADATA
kukufuckingkan-0.6.dist-info/WHEEL
kukufuckingkan-0.6.dist-info/top_level.txt
kukufuckingkan-0.6.dist-info/RECORD
