Metadata-Version: 2.1
Name: kukufuckingkan
Version: 0.6
Requires-Dist: requests
Requires-Dist: flask
